cane/__init__.py
cane-2.3.3.dist-info/licenses/LICENSE.txt
cane-2.3.3.dist-info/METADATA
cane-2.3.3.dist-info/WHEEL
cane-2.3.3.dist-info/top_level.txt
cane-2.3.3.dist-info/RECORD
