Metadata-Version: 2.4
Name: cane
Version: 2.3.3
Summary: Cane - Categorical Attribute traNsformation Environment
Home-page: https://github.com/Metalkiler/Cane-Categorical-Attribute-traNsformation-Environment
Author: Luís Miguel Matos, João Azevedo, Arthur Matta, André Pilastri, Paulo Cortez, Rui Mendes
Author-email: luis.matos@dsi.uminho.pt
License: MIT
Classifier: Programming Language :: Python :: 3
Classifier: License :: OSI Approved :: MIT License
Classifier: Operating System :: OS Independent
Requires-Python: >=3.6
License-File: LICENSE.txt
Requires-Dist: bounded-pool-executor
Requires-Dist: numpy
Requires-Dist: pandas
Requires-Dist: pqdm
Requires-Dist: python-dateutil
Requires-Dist: pytz
Requires-Dist: tqdm
Requires-Dist: typing-extensions
Requires-Dist: scikit-learn
Requires-Dist: pyspark
Requires-Dist: pyarrow
Dynamic: author
Dynamic: author-email
Dynamic: classifier
Dynamic: description
Dynamic: description-content-type
Dynamic: home-page
Dynamic: license
Dynamic: license-file
Dynamic: requires-dist
Dynamic: requires-python
Dynamic: summary
